levenshtein/__init__.py
levenshtein/main.py
levenshtein_package-0.0.2.dist-info/LICENSE
levenshtein_package-0.0.2.dist-info/METADATA
levenshtein_package-0.0.2.dist-info/WHEEL
levenshtein_package-0.0.2.dist-info/top_level.txt
levenshtein_package-0.0.2.dist-info/RECORD
